slurm_jupyter_kernel/__init__.py
slurm_jupyter_kernel/__main__.py
slurm_jupyter_kernel/provisioner.py
slurm_jupyter_kernel/script_template.py
slurm_jupyter_kernel/kernel_scripts/ijulia.sh
slurm_jupyter_kernel/kernel_scripts/ipython.sh
slurm_jupyter_kernel-1.9.data/scripts/slurmkernel
slurm_jupyter_kernel-1.9.dist-info/LICENSE
slurm_jupyter_kernel-1.9.dist-info/METADATA
slurm_jupyter_kernel-1.9.dist-info/WHEEL
slurm_jupyter_kernel-1.9.dist-info/entry_points.txt
slurm_jupyter_kernel-1.9.dist-info/top_level.txt
slurm_jupyter_kernel-1.9.dist-info/RECORD
