Metadata-Version: 2.1
Name: slurm-jupyter-kernel
Version: 1.9
Summary: Manage and start jupyter slurm kernels
Home-page: https://github.com/pc2/slurm_jupyter_kernel
Author: Marcel-Brian Wilkowsky
Author-email: marcel.wilkowsky@uni-paderborn.de
Project-URL: Bug Tracker, https://github.com/pc2/slurm_jupyter_kernel/issues
Classifier: Programming Language :: Python :: 3
Classifier: License :: OSI Approved :: MIT License
License-File: LICENSE
Requires-Dist: pexpect (>=4.8.0)
Requires-Dist: ipython (>=8.5.0)
Requires-Dist: jupyter-client (>=7.3.5)
